odoo8_addon_l10n_br_account_service-8.0.2.0.0-py2.7-nspkg.pth
odoo_addons/l10n_br_account_service/__openerp__.py
odoo_addons/l10n_br_account_service/__init__.py
odoo_addons/l10n_br_account_service/README.rst
odoo_addons/l10n_br_account_service/security/l10n_br_account_service_security.xml
odoo_addons/l10n_br_account_service/security/ir.model.access.csv
odoo_addons/l10n_br_account_service/migrations/8.0.1.0.0/pre-migration.py
odoo_addons/l10n_br_account_service/models/product.py
odoo_addons/l10n_br_account_service/models/res_partner.py
odoo_addons/l10n_br_account_service/models/account_invoice.py
odoo_addons/l10n_br_account_service/models/l10n_br_account.py
odoo_addons/l10n_br_account_service/models/__init__.py
odoo_addons/l10n_br_account_service/models/res_company.py
odoo_addons/l10n_br_account_service/models/l10n_br_account_service.py
odoo_addons/l10n_br_account_service/i18n/pt_BR.po
odoo_addons/l10n_br_account_service/test/account_customer_invoice.yml
odoo_addons/l10n_br_account_service/test/account_invoice_refund.yml
odoo_addons/l10n_br_account_service/views/l10n_br_account_view.xml
odoo_addons/l10n_br_account_service/views/account_invoice_view.xml
odoo_addons/l10n_br_account_service/views/product_view.xml
odoo_addons/l10n_br_account_service/views/res_company_view.xml
odoo_addons/l10n_br_account_service/views/nfse/account_invoice_nfse_view.xml
odoo_addons/l10n_br_account_service/data/l10n_br_account_service_data.xml
odoo_addons/l10n_br_account_service/demo/product_demo.xml
odoo_addons/l10n_br_account_service/demo/l10n_br_account_service_demo.xml
odoo_addons/l10n_br_account_service/demo/account_tax_demo.xml
odoo_addons/l10n_br_account_service/demo/account_fiscal_position_rule_demo.xml
odoo8_addon_l10n_br_account_service-8.0.2.0.0.dist-info/top_level.txt
odoo8_addon_l10n_br_account_service-8.0.2.0.0.dist-info/WHEEL
odoo8_addon_l10n_br_account_service-8.0.2.0.0.dist-info/RECORD
odoo8_addon_l10n_br_account_service-8.0.2.0.0.dist-info/metadata.json
odoo8_addon_l10n_br_account_service-8.0.2.0.0.dist-info/DESCRIPTION.rst
odoo8_addon_l10n_br_account_service-8.0.2.0.0.dist-info/METADATA
odoo8_addon_l10n_br_account_service-8.0.2.0.0.dist-info/namespace_packages.txt
